irradpy2/_init_.py
irradpy2/bsrn.py
irradpy2/midc.py
irradpy2/necessary_main.py
irradpy2/prediction.py
irradpy2/sauran.py
irradpy2/solrad.py
irradpy2/srml.py
irradpy2/surfrad.py
irradpy2-0.2.6.dist-info/licenses/LICENSE
irradpy2-0.2.6.dist-info/METADATA
irradpy2-0.2.6.dist-info/WHEEL
irradpy2-0.2.6.dist-info/top_level.txt
irradpy2-0.2.6.dist-info/RECORD
