Metadata-Version: 2.4
Name: irradpy2
Version: 0.2.6
Summary: Multi-source solar radiation downloader and forecasting toolkit
Author-email: Your Name <your@email.com>
License: MIT
Project-URL: Homepage, https://github.com/yourname/irradpy2
Keywords: solar,radiation,forecasting,BSRN,MIDC,SRML
Classifier: Programming Language :: Python :: 3
Classifier: License :: OSI Approved :: MIT License
Classifier: Operating System :: OS Independent
Requires-Python: >=3.9
License-File: LICENSE
Requires-Dist: numpy
Requires-Dist: pandas
Requires-Dist: requests
Requires-Dist: pytz
Requires-Dist: scikit-learn
Requires-Dist: torch
Dynamic: license-file
